OpenOPC.py
OpenOPC_WF-1.3.3.dist-info/LICENSE.txt
OpenOPC_WF-1.3.3.dist-info/METADATA
OpenOPC_WF-1.3.3.dist-info/WHEEL
OpenOPC_WF-1.3.3.dist-info/top_level.txt
OpenOPC_WF-1.3.3.dist-info/RECORD
